douyuquiz/__init__.py
douyuquiz/douyu_quiz.py
douyuquiz-0.2.dist-info/LICENSE
douyuquiz-0.2.dist-info/METADATA
douyuquiz-0.2.dist-info/WHEEL
douyuquiz-0.2.dist-info/top_level.txt
douyuquiz-0.2.dist-info/RECORD
