Metadata-Version: 2.1
Name: douyuquiz
Version: 0.2
Summary: Acquire douyu quiz information
Home-page: https://github.com/youbao88/douyuquiz
Author: Minhao Zhou
Author-email: youbao2@hotmail.com
License: UNKNOWN
Platform: UNKNOWN
Classifier: Programming Language :: Python :: 3
Classifier: License :: OSI Approved :: MIT License
Classifier: Operating System :: OS Independent
